setup.py
salure_helpers/ftp/__init__.py
salure_helpers/ftp/ftps.py
salure_helpers/ftp/sftp.py
salure_helpers_ftp.egg-info/PKG-INFO
salure_helpers_ftp.egg-info/SOURCES.txt
salure_helpers_ftp.egg-info/dependency_links.txt
salure_helpers_ftp.egg-info/not-zip-safe
salure_helpers_ftp.egg-info/requires.txt
salure_helpers_ftp.egg-info/top_level.txt