Metadata-Version: 1.0
Name: salure-helpers-ftp
Version: 2.0.0
Summary: FTP wrapper from Salure
Home-page: UNKNOWN
Author: D&A Salure
Author-email: support@salureconnnect.com
License: Salure License
Platform: UNKNOWN
